<properties>
  <property id="summary" iscontainer="true" ordering="1">Summary</property>
  <property id="body" iscontainer="true" ordering="2">Body</property>
  <property id="conclusion" iscontainer="true" ordering="3">Conclusion</property>

  <property id="headline" ordering="10">Headline</property>
  <property id="byline" ordering="11">By Line</property>
  <property id="lead" ordering="12">Lead</property>
  <property id="synopsis" ordering="13">Synopsis</property>
  <property id="publisheddate" ordering="14">Date</property>

  <property id="featureimage" ordering="21">Feature Image</property>
  <property id="featurevideo" ordering="22">Feature Video</property>
  <property id="featureaudio" ordering="23">Feature Audio</property>

  <property id="topiclist" ordering="31">Topics</property>

  <property id="imageright" ordering="41">Image Right</property>
  <property id="imageleft" ordering="42">Image Left</property>

  <property id="usefullink" ordering="51">Useful Link</property>

</properties>
