<?xml version="1.0" encoding="UTF-8"?>

<properties beanname="dataSearcher">
  <property id="question" index="true" stored="true" editable="true" viewtype="textarea">Question 
    <name>
      <language id="en"><![CDATA[Question]]></language>
    </name>
  </property>
  <property id="option_a" index="true" editable="true" stored="true" viewtype="text">Option (A)
    <name>
      <language id="en"><![CDATA[Option (A)]]></language>
    </name>
  </property>
  <property id="option_b" index="true" editable="true" stored="true" viewtype="text">Option (B) 
    <name>
      <language id="en"><![CDATA[Option (B)]]></language>
    </name>
  </property>
  <property id="option_c" index="true" editable="true" stored="true" viewtype="text">Option (C) 
    <name>
      <language id="en"><![CDATA[Option (C)]]></language>
    </name>
  </property>
  <property id="option_d" index="true" editable="true" stored="true" viewtype="text">Option (D) 
    <name>
      <language id="en"><![CDATA[Option (D)]]></language>
    </name>
  </property>
  <property id="mcqoptions" type="list" index="true" editable="true" stored="true">Correct Option
    <name>
      <language id="en"><![CDATA[Correct Option]]></language>
    </name>
  </property>
  <property id="rationale" index="true" editable="true" stored="true" viewtype="textarea">Rationale 
    <name>
      <language id="en"><![CDATA[Rationale]]></language>
    </name>
  </property>
  <property id="grade" index="true" editable="true" stored="true" type="number" datatype="number">Grade 
    <name>
      <language id="en"><![CDATA[Grade]]></language>
    </name>
  </property>
  <property id="mcqcognitivelevel" type="list" index="true" editable="true" stored="true">Cognitive Level 
    <name>
      <language id="en"><![CDATA[Cognitive Level]]></language>
    </name>
  </property>
</properties>
