<datas>
    <data id="asset_editstatus_1" icon="bi bi-card-text badge-pending" >Pending</data>
    <data id="asset_editstatus_rejected" icon="bi bi-card-text badge-rejected">Rejected</data>
    <data id="asset_editstatus_7" icon="bi bi-archive-fill" >Deleted</data>
    <data id="asset_duplicate_true" icon="bi bi-files" >Duplicate</data>
    <data id="asset_assetexpired_true" >Asset is Expired</data>
    <data id="asset_haschat_true" icon="bi bi-chat-left-text-fill">Chats</data>
    <data id="asset_islocked_true" icon="bi bi-lock-fill" >Locked</data>
    <data id="asset_deleted_true" icon="bi bi-archive-fill">Deleted</data>
    
</datas>                                                                                                                                                                                                    