<records>
   <data id="smartcreator_createmarketing" ordering="10" scenarioicon="calendar3">
      <name>
         <language id="en"><![CDATA[Create Weekly Marketing Assets]]></language>
      </name>
   </data>

   <data id="smartcreator_postsocialmedia" ordering="20">
      <name>
         <language id="en"><![CDATA[Create Daily Social Media Posts]]></language>
      </name>
   </data>

   <data id="informatics" ordering="30" scenarioicon="robot">
      <name>
         <language id="en"><![CDATA[Informatics]]></language>
      </name>
   </data>
   <data id="smartcreator_publish" ordering="40" scenarioicon="file-earmark-richtext">
      <name>
         <language id="en"><![CDATA[Smart Creator - Publish]]></language>
      </name>
   </data>

   <data id="email" ordering="50" scenarioicon="envelope-fill">
      <name>
         <language id="en"><![CDATA[Email research question]]></language>
      </name>
   </data>
   
</records>